churneval/__init__.py
churneval/churneval.py
churneval-1.3.dist-info/LICENSE.txt
churneval-1.3.dist-info/METADATA
churneval-1.3.dist-info/WHEEL
churneval-1.3.dist-info/top_level.txt
churneval-1.3.dist-info/RECORD
