Metadata-Version: 2.1
Name: churneval
Version: 1.3
Summary: churneval is a python package for evaluating churn models
Home-page: UNKNOWN
Author: Soumi De
Author-email: soumi.de@res.christuniversity.in
License: LICENSE.txt
Platform: UNKNOWN
Requires-Python: >=3.5
License-File: LICENSE.txt
Requires-Dist: churneval
Requires-Dist: pandas
Requires-Dist: sklearn
Requires-Dist: matplotlib
